tec_ml_toolbox/__init__.py
tec_ml_toolbox/tec_dat.py
tec_ml_toolbox-0.0.3.dist-info/METADATA
tec_ml_toolbox-0.0.3.dist-info/WHEEL
tec_ml_toolbox-0.0.3.dist-info/RECORD
